metrics_layer/__init__.py
metrics_layer/cli/__init__.py
metrics_layer/cli/cli_commands.py
metrics_layer/cli/seeding.py
metrics_layer/core/__init__.py
metrics_layer/core/convert/__init__.py
metrics_layer/core/convert/convert.py
metrics_layer/core/exceptions.py
metrics_layer/core/model/__init__.py
metrics_layer/core/model/base.py
metrics_layer/core/model/dashboard.py
metrics_layer/core/model/definitions.py
metrics_layer/core/model/field.py
metrics_layer/core/model/filter.py
metrics_layer/core/model/join.py
metrics_layer/core/model/join_graph.py
metrics_layer/core/model/model.py
metrics_layer/core/model/project.py
metrics_layer/core/model/relationship.py
metrics_layer/core/model/set.py
metrics_layer/core/model/topic.py
metrics_layer/core/model/view.py
metrics_layer/core/model/week_start_day_types.py
metrics_layer/core/parse/.gitignore
metrics_layer/core/parse/__init__.py
metrics_layer/core/parse/connections.py
metrics_layer/core/parse/github_repo.py
metrics_layer/core/parse/manifest.py
metrics_layer/core/parse/project_dumper.py
metrics_layer/core/parse/project_loader.py
metrics_layer/core/parse/project_reader_base.py
metrics_layer/core/parse/project_reader_metricflow.py
metrics_layer/core/parse/project_reader_metrics_layer.py
metrics_layer/core/query/__init__.py
metrics_layer/core/query/query.py
metrics_layer/core/sql/__init__.py
metrics_layer/core/sql/arbitrary_merge_resolve.py
metrics_layer/core/sql/merged_query_resolve.py
metrics_layer/core/sql/query_arbitrary_merged_queries.py
metrics_layer/core/sql/query_base.py
metrics_layer/core/sql/query_cumulative_metric.py
metrics_layer/core/sql/query_design.py
metrics_layer/core/sql/query_dialect.py
metrics_layer/core/sql/query_errors.py
metrics_layer/core/sql/query_filter.py
metrics_layer/core/sql/query_funnel.py
metrics_layer/core/sql/query_generator.py
metrics_layer/core/sql/query_merged_results.py
metrics_layer/core/sql/resolve.py
metrics_layer/core/sql/single_query_resolve.py
metrics_layer/core/utils.py
metrics_layer-0.16.26.dist-info/LICENSE
metrics_layer-0.16.26.dist-info/METADATA
metrics_layer-0.16.26.dist-info/WHEEL
metrics_layer-0.16.26.dist-info/entry_points.txt
metrics_layer-0.16.26.dist-info/RECORD
