Metadata-Version: 2.1
Name: metrics_layer
Version: 0.16.26
Summary: The open source metrics layer.
Home-page: https://github.com/Zenlytic/metrics_layer
License: Apache 2.0
Keywords: Metrics Layer,Business Intelligence,Analytics
Author: Paul Blankley
Author-email: paul@zenlytic.com
Requires-Python: >=3.9,<3.13
Classifier: License :: Other/Proprietary License
Classifier: Programming Language :: Python :: 3
Classifier: Programming Language :: Python :: 3.9
Classifier: Programming Language :: Python :: 3.10
Classifier: Programming Language :: Python :: 3.11
Classifier: Programming Language :: Python :: 3.12
Provides-Extra: all
Provides-Extra: bigquery
Provides-Extra: postgres
Provides-Extra: redshift
Provides-Extra: snowflake
Requires-Dist: GitPython (>=3.1.20)
Requires-Dist: PyPika (>=0.48.8,<0.49.0)
Requires-Dist: PyYAML (>=6.0,<7.0)
Requires-Dist: SQLAlchemy (>=2.0.21,<3.0.0)
Requires-Dist: click (>=8.0,<9.0)
Requires-Dist: colorama (>=0.4.4,<0.5.0)
Requires-Dist: google-cloud-bigquery (>=3.13.0,<4.0.0) ; extra == "bigquery" or extra == "all"
Requires-Dist: jinja2 (>=3.1.2,<4.0.0)
Requires-Dist: networkx (>=2.8.2,<3.0.0)
Requires-Dist: numpy (>=1.24.4,<2.0.0)
Requires-Dist: pandas (>=1.5.2,<2.0.0)
Requires-Dist: pendulum (>=3.0.0,<4.0.0)
Requires-Dist: psycopg2-binary (>=2.9.9,<3.0.0) ; extra == "postgres" or extra == "all"
Requires-Dist: pyarrow (>=10) ; extra == "snowflake" or extra == "bigquery" or extra == "all"
Requires-Dist: redshift-connector (>=2.0.905,<3.0.0) ; extra == "redshift" or extra == "all"
Requires-Dist: ruamel.yaml (>=0.17.20,<0.18.0)
Requires-Dist: snowflake-connector-python (>=3.5.0,<4.0.0) ; extra == "snowflake" or extra == "all"
Requires-Dist: sqlglot[rs] (>=27.2.0,<28.0.0)
Requires-Dist: sqlparse (>=0.4.1)
Project-URL: Documentation, https://docs.zenlytic.com
Project-URL: Repository, https://github.com/Zenlytic/metrics_layer
